vavista_rpc/__init__.py
vavista_rpc/brokerRPC3.py
vavista_rpc-0.0.13.dist-info/COPYING
vavista_rpc-0.0.13.dist-info/LICENSE
vavista_rpc-0.0.13.dist-info/METADATA
vavista_rpc-0.0.13.dist-info/WHEEL
vavista_rpc-0.0.13.dist-info/top_level.txt
vavista_rpc-0.0.13.dist-info/RECORD
