Metadata-Version: 2.2
Name: vavista_rpc
Version: 0.0.13
Summary: VAVista RPC interface
Home-page: https://github.com/vernonOber/vavista-rpc3
Author: Conor Dowling, Kevin Gill
Author-email: vo2521@gmail.com
Classifier: Programming Language :: Python :: 3
Classifier: License :: OSI Approved :: GNU Affero General Public License v3 or later (AGPLv3+)
Classifier: Operating System :: OS Independent
Requires-Python: >=3.6
License-File: LICENSE
License-File: COPYING
Dynamic: author
Dynamic: author-email
Dynamic: classifier
Dynamic: description
Dynamic: home-page
Dynamic: requires-python
Dynamic: summary
